responsible_ai/__init__.py
responsible_ai-0.0.1.dist-info/LICENSE.txt
responsible_ai-0.0.1.dist-info/METADATA
responsible_ai-0.0.1.dist-info/WHEEL
responsible_ai-0.0.1.dist-info/top_level.txt
responsible_ai-0.0.1.dist-info/RECORD
